Workbook
Name Slicer_Category: #N/A
Name Slicer_Payment_Mode: #N/A

Sheet Sales Register
A1: Restaurant Daily Sales Register - Sales Data
A2: Date | B2: Menu Item | C2: Category | D2: Quantity Sold | E2: Unit Price (₹) | F2: Total Sales (₹) | G2: Payment Mode | H2: Discount Eligibility | I2: Payment Mode Check
A3: 46296 | B3: Chicken Biryani | C3: Food | D3: 11 | E3: 200 | F3: =D3*E3 -> 2200 | G3: Card | H3: =IF(AND(D3>50,C3="Beverages"),"Eligible","Not Eligible") -> Not Eligible | I3: =IF(OR(UPPER(G3)="CARD",UPPER(G3)="UPI"),"Digital",IF(UPPER(G3)="CASH","Cash"," ")) -> Digital
A4: 46296 | B4: Chicken Biryani | C4: Food | D4: 10 | E4: 200 | F4: =D4*E4 -> 2000 | G4: UPI | H4: =IF(AND(D4>50,C4="Beverages"),"Eligible","Not Eligible") -> Not Eligible | I4: =IF(OR(UPPER(G4)="CARD",UPPER(G4)="UPI"),"Digital",IF(UPPER(G4)="CASH","Cash"," ")) -> Digital
A5: 46296 | B5: Fresh Lime Juice | C5: Beverages | D5: 52 | E5: 70 | F5: =D5*E5 -> 3640 | G5: Cash | H5: =IF(AND(D5>50,C5="Beverages"),"Eligible","Not Eligible") -> Eligible | I5: =IF(OR(UPPER(G5)="CARD",UPPER(G5)="UPI"),"Digital",IF(UPPER(G5)="CASH","Cash"," ")) -> Cash
A6: 46296 | B6: Chicken Biryani | C6: Food | D6: 10 | E6: 200 | F6: =D6*E6 -> 2000 | G6: UPI | H6: =IF(AND(D6>50,C6="Beverages"),"Eligible","Not Eligible") -> Not Eligible | I6: =IF(OR(UPPER(G6)="CARD",UPPER(G6)="UPI"),"Digital",IF(UPPER(G6)="CASH","Cash"," ")) -> Digital
A7: 46296 | B7: Chicken Biryani | C7: Food | D7: 9 | E7: 200 | F7: =D7*E7 -> 1800 | G7: UPI | H7: =IF(AND(D7>50,C7="Beverages"),"Eligible","Not Eligible") -> Not Eligible | I7: =IF(OR(UPPER(G7)="CARD",UPPER(G7)="UPI"),"Digital",IF(UPPER(G7)="CASH","Cash"," ")) -> Digital
A8: 46296 | B8: Paneer Wrap | C8: Food | D8: 16 | E8: 180 | F8: =D8*E8 -> 2880 | G8: Card | H8: =IF(AND(D8>50,C8="Beverages"),"Eligible","Not Eligible") -> Not Eligible | I8: =IF(OR(UPPER(G8)="CARD",UPPER(G8)="UPI"),"Digital",IF(UPPER(G8)="CASH","Cash"," ")) -> Digital
A9: 46297 | B9: Veg Biryani | C9: Food | D9: 3 | E9: 160 | F9: =D9*E9 -> 480 | G9: UPI | H9: =IF(AND(D9>50,C9="Beverages"),"Eligible","Not Eligible") -> Not Eligible | I9: =IF(OR(UPPER(G9)="CARD",UPPER(G9)="UPI"),"Digital",IF(UPPER(G9)="CASH","Cash"," ")) -> Digital
A10: 46297 | B10: Chicken Biryani | C10: Food | D10: 16 | E10: 200 | F10: =D10*E10 -> 3200 | G10: Card | H10: =IF(AND(D10>50,C10="Beverages"),"Eligible","Not Eligible") -> Not Eligible | I10: =IF(OR(UPPER(G10)="CARD",UPPER(G10)="UPI"),"Digital",IF(UPPER(G10)="CASH","Cash"," ")) -> Digital
A11: 46297 | B11: Chicken Biryani | C11: Food | D11: 13 | E11: 200 | F11: =D11*E11 -> 2600 | G11: Cash | H11: =IF(AND(D11>50,C11="Beverages"),"Eligible","Not Eligible") -> Not Eligible | I11: =IF(OR(UPPER(G11)="CARD",UPPER(G11)="UPI"),"Digital",IF(UPPER(G11)="CASH","Cash"," ")) -> Cash
A12: 46297 | B12: Margherita Pizza | C12: Food | D12: 14 | E12: 250 | F12: =D12*E12 -> 3500 | G12: UPI | H12: =IF(AND(D12>50,C12="Beverages"),"Eligible","Not Eligible") -> Not Eligible | I12: =IF(OR(UPPER(G12)="CARD",UPPER(G12)="UPI"),"Digital",IF(UPPER(G12)="CASH","Cash"," ")) -> Digital
A13: 46297 | B13: French Fries | C13: Food | D13: 4 | E13: 120 | F13: =D13*E13 -> 480 | G13: UPI | H13: =IF(AND(D13>50,C13="Beverages"),"Eligible","Not Eligible") -> Not Eligible | I13: =IF(OR(UPPER(G13)="CARD",UPPER(G13)="UPI"),"Digital",IF(UPPER(G13)="CASH","Cash"," ")) -> Digital
A14: 46297 | B14: Cheese Burger | C14: Food | D14: 60 | E14: 220 | F14: =D14*E14 -> 13200 | G14: Cash | H14: =IF(AND(D14>50,C14="Beverages"),"Eligible","Not Eligible") -> Not Eligible | I14: =IF(OR(UPPER(G14)="CARD",UPPER(G14)="UPI"),"Digital",IF(UPPER(G14)="CASH","Cash"," ")) -> Cash
... A161: 46325 | B161: French Fries | C161: Food | D161: 6 | E161: 120 | F161: =D161*E161 -> 720 | G161: UPI | H161: =IF(AND(D161>50,C161="Beverages"),"Eligible","Not Eligible") -> Not Eligible | I161: =IF(OR(UPPER(G161)="CARD",UPPER(G161)="UPI"),"Digital",IF(UPPER(G161)="CASH","Cash"," ")) -> Digital
I162: =IF(OR(UPPER(G162)="CARD",UPPER(G162)="UPI"),"Digital",IF(UPPER(G162)="CASH","Cash"," "))

Sheet Daily Summary
A1: Daily Summary - Aggregated View
A2: Date | B2: Total Sales (₹) | C2: Daily Target (₹) | D2: Target Status | E2: Sales Level | F2: Discount Eligible Items | G2: Peak Day Alert
A3: 46296 | B3: =SUMIF('Sales Register'!$A:$A, A3, 'Sales Register'!$F:$F) -> 14520 | C3: 15000 | D3: =IF(B3>=C3,"Target Met","Below Target") -> Below Target | E3: =IF(B3>=C3,"High Sale", IF(B3>=8000,"Average Sale","Low Sale")) -> Average Sale | F3: =COUNTIFS('Sales Register'!$A:$A,A3,'Sales Register'!$H:$H,"Eligible") -> 1 | G3: =IF(B3=MAX($B$3:$B$32),"Peak Day", "-") -> -
A4: 46297 | B4: =SUMIF('Sales Register'!$A:$A, A4, 'Sales Register'!$F:$F) -> 23460 | C4: 15000 | D4: =IF(B4>=C4,"Target Met","Below Target") -> Target Met | E4: =IF(B4>=C4,"High Sale", IF(B4>=8000,"Average Sale","Low Sale")) -> High Sale | F4: =COUNTIFS('Sales Register'!$A:$A,A4,'Sales Register'!$H:$H,"Eligible") -> 0 | G4: =IF(B4=MAX($B$3:$B$32),"Peak Day", "-") -> -
A5: 46298 | B5: =SUMIF('Sales Register'!$A:$A, A5, 'Sales Register'!$F:$F) -> 17020 | C5: 15000 | D5: =IF(B5>=C5,"Target Met","Below Target") -> Target Met | E5: =IF(B5>=C5,"High Sale", IF(B5>=8000,"Average Sale","Low Sale")) -> High Sale | F5: =COUNTIFS('Sales Register'!$A:$A,A5,'Sales Register'!$H:$H,"Eligible") -> 0 | G5: =IF(B5=MAX($B$3:$B$32),"Peak Day", "-") -> - | I5: Key Insights
A6: 46299 | B6: =SUMIF('Sales Register'!$A:$A, A6, 'Sales Register'!$F:$F) -> 16500 | C6: 15000 | D6: =IF(B6>=C6,"Target Met","Below Target") -> Target Met | E6: =IF(B6>=C6,"High Sale", IF(B6>=8000,"Average Sale","Low Sale")) -> High Sale | F6: =COUNTIFS('Sales Register'!$A:$A,A6,'Sales Register'!$H:$H,"Eligible") -> 1 | G6: =IF(B6=MAX($B$3:$B$32),"Peak Day", "-") -> - | I6: Total Revenue | J6: =SUM(B3:B32) -> 413010
A7: 46300 | B7: =SUMIF('Sales Register'!$A:$A, A7, 'Sales Register'!$F:$F) -> 13810 | C7: 15000 | D7: =IF(B7>=C7,"Target Met","Below Target") -> Below Target | E7: =IF(B7>=C7,"High Sale", IF(B7>=8000,"Average Sale","Low Sale")) -> Average Sale | F7: =COUNTIFS('Sales Register'!$A:$A,A7,'Sales Register'!$H:$H,"Eligible") -> 0 | G7: =IF(B7=MAX($B$3:$B$32),"Peak Day", "-") -> - | I7: Average Daily Sales | J7: =AVERAGE(B3:B32) -> 13767
A8: 46301 | B8: =SUMIF('Sales Register'!$A:$A, A8, 'Sales Register'!$F:$F) -> 7850 | C8: 15000 | D8: =IF(B8>=C8,"Target Met","Below Target") -> Below Target | E8: =IF(B8>=C8,"High Sale", IF(B8>=8000,"Average Sale","Low Sale")) -> Low Sale | F8: =COUNTIFS('Sales Register'!$A:$A,A8,'Sales Register'!$H:$H,"Eligible") -> 0 | G8: =IF(B8=MAX($B$3:$B$32),"Peak Day", "-") -> - | I8: Total Orders | J8: =COUNTA('Sales Register'!A3:A1000) -> 159
A9: 46302 | B9: =SUMIF('Sales Register'!$A:$A, A9, 'Sales Register'!$F:$F) -> 6230 | C9: 15000 | D9: =IF(B9>=C9,"Target Met","Below Target") -> Below Target | E9: =IF(B9>=C9,"High Sale", IF(B9>=8000,"Average Sale","Low Sale")) -> Low Sale | F9: =COUNTIFS('Sales Register'!$A:$A,A9,'Sales Register'!$H:$H,"Eligible") -> 0 | G9: =IF(B9=MAX($B$3:$B$32),"Peak Day", "-") -> - | I9: Days Target Met | J9: =COUNTIF(D3:D32,"Target Met")&" / "&COUNTA(D3:D32) -> 16 / 30
A10: 46303 | B10: =SUMIF('Sales Register'!$A:$A, A10, 'Sales Register'!$F:$F) -> 17590 | C10: 15000 | D10: =IF(B10>=C10,"Target Met","Below Target") -> Target Met | E10: =IF(B10>=C10,"High Sale", IF(B10>=8000,"Average Sale","Low Sale")) -> High Sale | F10: =COUNTIFS('Sales Register'!$A:$A,A10,'Sales Register'!$H:$H,"Eligible") -> 0 | G10: =IF(B10=MAX($B$3:$B$32),"Peak Day", "-") -> - | I10: Target Achievement Rate | J10: =COUNTIF(D3:D32,"Target Met")/COUNTA(D3:D32) -> 0.53333333
A11: 46304 | B11: =SUMIF('Sales Register'!$A:$A, A11, 'Sales Register'!$F:$F) -> 20970 | C11: 15000 | D11: =IF(B11>=C11,"Target Met","Below Target") -> Target Met | E11: =IF(B11>=C11,"High Sale", IF(B11>=8000,"Average Sale","Low Sale")) -> High Sale | F11: =COUNTIFS('Sales Register'!$A:$A,A11,'Sales Register'!$H:$H,"Eligible") -> 2 | G11: =IF(B11=MAX($B$3:$B$32),"Peak Day", "-") -> -
A12: 46305 | B12: =SUMIF('Sales Register'!$A:$A, A12, 'Sales Register'!$F:$F) -> 16440 | C12: 15000 | D12: =IF(B12>=C12,"Target Met","Below Target") -> Target Met | E12: =IF(B12>=C12,"High Sale", IF(B12>=8000,"Average Sale","Low Sale")) -> High Sale | F12: =COUNTIFS('Sales Register'!$A:$A,A12,'Sales Register'!$H:$H,"Eligible") -> 0 | G12: =IF(B12=MAX($B$3:$B$32),"Peak Day", "-") -> -
A13: 46306 | B13: =SUMIF('Sales Register'!$A:$A, A13, 'Sales Register'!$F:$F) -> 10030 | C13: 15000 | D13: =IF(B13>=C13,"Target Met","Below Target") -> Below Target | E13: =IF(B13>=C13,"High Sale", IF(B13>=8000,"Average Sale","Low Sale")) -> Average Sale | F13: =COUNTIFS('Sales Register'!$A:$A,A13,'Sales Register'!$H:$H,"Eligible") -> 1 | G13: =IF(B13=MAX($B$3:$B$32),"Peak Day", "-") -> -
A14: 46307 | B14: =SUMIF('Sales Register'!$A:$A, A14, 'Sales Register'!$F:$F) -> 9040 | C14: 15000 | D14: =IF(B14>=C14,"Target Met","Below Target") -> Below Target | E14: =IF(B14>=C14,"High Sale", IF(B14>=8000,"Average Sale","Low Sale")) -> Average Sale | F14: =COUNTIFS('Sales Register'!$A:$A,A14,'Sales Register'!$H:$H,"Eligible") -> 0 | G14: =IF(B14=MAX($B$3:$B$32),"Peak Day", "-") -> -
A15: 46308 | B15: =SUMIF('Sales Register'!$A:$A, A15, 'Sales Register'!$F:$F) -> 25760 | C15: 15000 | D15: =IF(B15>=C15,"Target Met","Below Target") -> Target Met | E15: =IF(B15>=C15,"High Sale", IF(B15>=8000,"Average Sale","Low Sale")) -> High Sale | F15: =COUNTIFS('Sales Register'!$A:$A,A15,'Sales Register'!$H:$H,"Eligible") -> 0 | G15: =IF(B15=MAX($B$3:$B$32),"Peak Day", "-") -> Peak Day
A16: 46309 | B16: =SUMIF('Sales Register'!$A:$A, A16, 'Sales Register'!$F:$F) -> 7810 | C16: 15000 | D16: =IF(B16>=C16,"Target Met","Below Target") -> Below Target | E16: =IF(B16>=C16,"High Sale", IF(B16>=8000,"Average Sale","Low Sale")) -> Low Sale | F16: =COUNTIFS('Sales Register'!$A:$A,A16,'Sales Register'!$H:$H,"Eligible") -> 1 | G16: =IF(B16=MAX($B$3:$B$32),"Peak Day", "-") -> -
A17: 46310 | B17: =SUMIF('Sales Register'!$A:$A, A17, 'Sales Register'!$F:$F) -> 13050 | C17: 15000 | D17: =IF(B17>=C17,"Target Met","Below Target") -> Below Target | E17: =IF(B17>=C17,"High Sale", IF(B17>=8000,"Average Sale","Low Sale")) -> Average Sale | F17: =COUNTIFS('Sales Register'!$A:$A,A17,'Sales Register'!$H:$H,"Eligible") -> 0 | G17: =IF(B17=MAX($B$3:$B$32),"Peak Day", "-") -> -
A18: 46311 | B18: =SUMIF('Sales Register'!$A:$A, A18, 'Sales Register'!$F:$F) -> 19350 | C18: 15000 | D18: =IF(B18>=C18,"Target Met","Below Target") -> Target Met | E18: =IF(B18>=C18,"High Sale", IF(B18>=8000,"Average Sale","Low Sale")) -> High Sale | F18: =COUNTIFS('Sales Register'!$A:$A,A18,'Sales Register'!$H:$H,"Eligible") -> 0 | G18: =IF(B18=MAX($B$3:$B$32),"Peak Day", "-") -> -
A19: 46312 | B19: =SUMIF('Sales Register'!$A:$A, A19, 'Sales Register'!$F:$F) -> 16300 | C19: 15000 | D19: =IF(B19>=C19,"Target Met","Below Target") -> Target Met | E19: =IF(B19>=C19,"High Sale", IF(B19>=8000,"Average Sale","Low Sale")) -> High Sale | F19: =COUNTIFS('Sales Register'!$A:$A,A19,'Sales Register'!$H:$H,"Eligible") -> 0 | G19: =IF(B19=MAX($B$3:$B$32),"Peak Day", "-") -> -
A20: 46313 | B20: =SUMIF('Sales Register'!$A:$A, A20, 'Sales Register'!$F:$F) -> 6190 | C20: 15000 | D20: =IF(B20>=C20,"Target Met","Below Target") -> Below Target | E20: =IF(B20>=C20,"High Sale", IF(B20>=8000,"Average Sale","Low Sale")) -> Low Sale | F20: =COUNTIFS('Sales Register'!$A:$A,A20,'Sales Register'!$H:$H,"Eligible") -> 0 | G20: =IF(B20=MAX($B$3:$B$32),"Peak Day", "-") -> -
A21: 46314 | B21: =SUMIF('Sales Register'!$A:$A, A21, 'Sales Register'!$F:$F) -> 16810 | C21: 15000 | D21: =IF(B21>=C21,"Target Met","Below Target") -> Target Met | E21: =IF(B21>=C21,"High Sale", IF(B21>=8000,"Average Sale","Low Sale")) -> High Sale | F21: =COUNTIFS('Sales Register'!$A:$A,A21,'Sales Register'!$H:$H,"Eligible") -> 0 | G21: =IF(B21=MAX($B$3:$B$32),"Peak Day", "-") -> -
A22: 46315 | B22: =SUMIF('Sales Register'!$A:$A, A22, 'Sales Register'!$F:$F) -> 15910 | C22: 15000 | D22: =IF(B22>=C22,"Target Met","Below Target") -> Target Met | E22: =IF(B22>=C22,"High Sale", IF(B22>=8000,"Average Sale","Low Sale")) -> High Sale | F22: =COUNTIFS('Sales Register'!$A:$A,A22,'Sales Register'!$H:$H,"Eligible") -> 0 | G22: =IF(B22=MAX($B$3:$B$32),"Peak Day", "-") -> -
... A32: 46325 | B32: =SUMIF('Sales Register'!$A:$A, A32, 'Sales Register'!$F:$F) -> 16480 | C32: 15000 | D32: =IF(B32>=C32,"Target Met","Below Target") -> Target Met | E32: =IF(B32>=C32,"High Sale", IF(B32>=8000,"Average Sale","Low Sale")) -> High Sale | F32: =COUNTIFS('Sales Register'!$A:$A,A32,'Sales Register'!$H:$H,"Eligible") -> 0 | G32: =IF(B32=MAX($B$3:$B$32),"Peak Day", "-") -> -

Sheet Sales Dashboard
A1: Tables | G1: RESTAURANT SALES DASHBOARD
A3: Row Labels | B3: Sum of Total Sales (₹) | D3: Row Labels | E3: Sum of Total Sales (₹)
A4: Beverages | B4: 41970 | D4: Card | E4: 115780
A5: Desserts | B5: 9450 | D5: Cash | E5: 121850
A6: Food | B6: 361590 | D6: UPI | E6: 175380
A7: Grand Total | B7: 413010 | D7: Grand Total | E7: 413010
A10: Row Labels | B10: Sum of Total Sales (₹)
A11: 46296 | B11: 14520
A12: 46297 | B12: 23460 | D12: Row Labels | E12: Sum of Total Sales (₹)
A13: 46298 | B13: 17020 | D13: Chicken Biryani | E13: 134400
A14: 46299 | B14: 16500 | D14: Margherita Pizza | E14: 92750
A15: 46300 | B15: 13810 | D15: Cheese Burger | E15: 58080
A16: 46301 | B16: 7850 | D16: Veg Biryani | E16: 41440
A17: 46302 | B17: 6230 | D17: Fresh Lime Juice | E17: 22400
A18: 46303 | B18: 17590 | D18: Grand Total | E18: 349070
A19: 46304 | B19: 20970
A20: 46305 | B20: 16440
A21: 46306 | B21: 10030
A22: 46307 | B22: 9040
A23: 46308 | B23: 25760
A24: 46309 | B24: 7810
A25: 46310 | B25: 13050
A26: 46311 | B26: 19350
A27: 46312 | B27: 16300
A28: 46313 | B28: 6190
A29: 46314 | B29: 16810
A30: 46315 | B30: 15910
... A40: 46325 | B40: 16480
A41: Grand Total | B41: 413010
